mdl/__init__.py
mdl/__main__.py
mdl/commons.py
mdl/downloader.py
mdl/utils.py
mdl/videoconfig.py
mdl/conf/dlops.conf
mdl/conf/misc.conf
mdl/log/mdl.log
mdl/sites/__init__.py
mdl/sites/m1905.py
mdl/sites/vqq.py
mdl/third_parties/__init__.py
mdl/third_parties/__main__.py
mdl/third_parties/aria2/README
mdl/third_parties/ffmpeg/README
mdl/third_parties/mkvtoolnix/README
mdl/third_parties/setupext_janitor/README.rst
mdl/third_parties/setupext_janitor/janitor.py
movie_downloader-0.1.0.dist-info/METADATA
movie_downloader-0.1.0.dist-info/WHEEL
movie_downloader-0.1.0.dist-info/entry_points.txt
movie_downloader-0.1.0.dist-info/top_level.txt
movie_downloader-0.1.0.dist-info/RECORD
